{
    "na'vi": "'u",
    "translations": [
        {
            "de": "Ding (Sache, Tatsache, Abstraktion)",
            "en": "thing (object, fact, abstraction)",
            "et": "asi (ese, fakt, mõte)",
            "fr": "chose | fait",
            "hu": "dolog (valami)",
            "nl": "ding (object, feit)",
            "pl": "rzecz (przedmiot, fakt, pojęcie)",
            "ru": "вещь",
            "sv": "sak, objekt"
        }
    ],
    "pronunciation": [
        "'u",
        1
    ],
    "source": "Taronyu's dictionary 9.58 < Frommer",
    "type": "n"
}