{
    "na'vi": "fyeyntu",
    "translations": [
        {
            "de": "Erwachsener, erwachsene Person",
            "en": "adult person",
            "et": "täiskasvanu",
            "fr": "adulte",
            "hu": "felnőtt személy",
            "nl": "volwassen persoon",
            "pl": "pełnoletni, dorosły (osoba dorosła)",
            "ru": "взрослый (о человеке)",
            "sv": "vuxen person"
        }
    ],
    "pronunciation": [
        "fyeyn-tu",
        1
    ],
    "source": "Frommers Blog (16. July 2010) http://naviteri.org/2010/07/vocabulary-update/",
    "type": "n"
}