{
    "na'vi": "ha'ngir",
    "translations": [
        {
            "de": "Nachmittag",
            "en": "afternoon",
            "et": "pärastlõuna",
            "fr": "après-midi",
            "hu": "délután",
            "nl": "middag",
            "pl": "popołudnie",
            "ru": "после полудня",
            "sv": "eftermiddag"
        }
    ],
    "pronunciation": [
        "ha'-ngir",
        2
    ],
    "source": "Frommer (18. June 2010) http://forum.learnnavi.org/language-updates/txelanit-hivawl/",
    "type": "n"
}