{
    "na'vi": "hawl",
    "translations": [
        {
            "de": "vorbereiten",
            "en": "prepare",
            "et": "(ette) valmistama",
            "hu": "készül(ődik)",
            "nl": "voorbereiden",
            "pl": "szykować",
            "ru": "готовить, подготавливать",
            "sv": "förbereda"
        }
    ],
    "pronunciation": [
        "hawl",
        1
    ],
    "infixes": "h..awl",
    "source": "Frommer (29 Jul 2012) http://naviteri.org/2012/07/tskxekengtsyip-a-mikyunfpi-a-little-listening-exercise/",
    "type": "v:tr"
}