{
    "na'vi": "hek",
    "translations": [
        {
            "de": "kurios sein, unerwartet sein",
            "en": "to be curious, odd, strange, unexpected",
            "et": "olema huvitav, imelik, kummaline, üllatav",
            "hu": "furcsának, különösnek, idegennek, váratlannak lenni",
            "nl": "benieuwd zijn, vreemd, onverwacht",
            "pl": "być dziwnym, niezwykłym, dziwacznym, niespodziewanym, osobliwym",
            "ru": "чудить, юродствовать",
            "sv": "vara annorlunda, konstig, oväntad, underlig"
        }
    ],
    "pronunciation": [
        "hek",
        1
    ],
    "infixes": "h..ek",
    "type": "v:in"
}
