{
    "na'vi": "kìmar",
    "translations": [
        {
            "de": "in Saison, Saison haben (für Nahrung, Gemüse und Tiere); für Tiere: rollig, läufig",
            "en": "in season (of foods, vegetable or animal)",
            "et": "hooajaline",
            "hu": "szezonális (étel, zöldség vagy állat)",
            "nl": "van dit seizoen (voeding, groente of dierlijk)",
            "pl": "sezonowy (o jedzeniu, roślinach lub zwierzętach)",
            "ru": "в сезон (растений или животных)",
            "sv": "i säsong (om mat, grönsaker och djur)"
        }
    ],
    "pronunciation": [
        "kì-mar",
        2
    ],
    "source": "Frommer (30.10.2011) http://naviteri.org/2011/10/more-vocabulary-a-bit-of-grammar/",
    "type": "adj"
}