{
    "na'vi": "nìksman",
    "translations": [
        {
            "de": "wunderbarerweise, fantastischerweise, tollerweise",
            "en": "wonderfully",
            "et": "vapustavalt",
            "fr": "merveilleusement",
            "hu": "csodálatosan",
            "nl": "geweldig (op een geweldige manier)",
            "pl": "wspaniale, cudownie, fantastycznie",
            "ru": "впечатляюще",
            "sv": "underbart"
        }
    ],
    "pronunciation": [
        "nìk-sman",
        2
    ],
    "source": "Frommer (24.09. 2011) http://naviteri.org/2011/09/miscellaneous-vocabulary/",
    "type": "adv"
}