{
    "na'vi": "nìmal",
    "translations": [
        {
            "de": "glaubhaft, ohne Zögern",
            "en": "trustingly, without hesitation",
            "et": "usaldavalt, kahtluseta",
            "fr": "avec confiance | sans hésitation",
            "hu": "bízva, habozás nélkül",
            "nl": "vertrouwend, zonder twijfel",
            "pl": "ufnie, bez wahania",
            "ru": "доверчиво"
        }
    ],
    "pronunciation": [
        "nì-mal",
        2
    ],
    "source": "Frommer (22. January 2012) http://naviteri.org/2012/01/more-additions-to-the-lexicon/",
    "type": "adv"
}