{
    "na'vi": "oeng",
    "translations": [
        {
            "de": "wir beide (dual inklusive), Du und Ich",
            "en": "we two, us two (dual inclusive), you and I",
            "et": "meie kaks (välistav), sina ja mina",
            "hu": "mi ketten (beleértő) (te és én)",
            "nl": "wij twee (tweevoudig inclusief)",
            "pl": "my dwaj, nas dwoje (inclusivus), ty i ja",
            "ru": "мы с тобой (двойственный инклюзив)",
            "sv": "vi två, du och jag"
        }
    ],
    "pronunciation": [
        "oeng",
        1
    ],
    "type": "pn"
}