{
    "na'vi": "pelì'u",
    "translations": [
        {
            "de": "welches Wort?, welche Äußerung?",
            "en": "what (word, utterance)",
            "et": "mis (sõna, väljend)",
            "hu": "milyen szó? ",
            "nl": "wat, welk (woord, uiting)",
            "pl": "jakie, które (słowo, wyrażenie)",
            "ru": "какое? что за? (вопрос к слову или высказыванию)",
            "sv": "vad (för ord)"
        }
    ],
    "pronunciation": [
        "pe-lì-'u",
        2
    ],
    "source": "Taronyu's Dictionary 10 < Frommer"
}