{
    "na'vi": "san",
    "translations": [
        {
            "de": "Zitat (siehe auch sìk)",
            "en": "(start-of-quote particle)",
            "et": "otsekõne algus",
            "hu": "idézet, függő beszéd kezdete",
            "nl": "gezegde, citaat",
            "pl": "rozpoczęcie cytowania",
            "ru": "маркер начала цитирования речи",
            "sv": "säga, citera"
        }
    ],
    "meaning_note": "Used together with [sìk:part] to mark a direct quote.",
    "pronunciation": [
        "san",
        1
    ],
    "type": "part",
    "seeAlso": [
        "sìk:part"
    ]
}
