{
    "na'vi": "tsap'alute",
    "translations": [
        {
            "de": "entschuldigen (sich)",
            "en": "apologise (apologize)",
            "et": "vabandama",
            "hu": "bocsánatot kér",
            "nl": "verontschuldigen",
            "pl": "przepraszać",
            "ru": "извиняться",
            "sv": "be om ursäkt"
        }
    ],
    "pronunciation": [
        "tsap-'a-lu-te",
        2
    ],
    "source": "Taronyu's Dictionary 9.53 < Frommer",
    "type": "n:si"
}