{
    "na'vi": "tsulfätu",
    "translations": [
        {
            "de": "Experte, Meister einer Fähigkeit, Kunst, Handwerk",
            "en": "master of an art, craft, or skill, expert",
            "et": "meister, ekspert (kunsti, käsitöö, oskuse)",
            "hu": "mester",
            "nl": "expert, meester van een vak, kunst of vaardigheid",
            "pl": "mistrz, ekspert",
            "ru": "умелец, эксперт",
            "sv": "expert, någon som har bemästrat en konst eller färdighet"
        }
    ],
    "pronunciation": [
        "tsul-fä-tu",
        2
    ],
    "source": "Frommer (24. June 2010) http://naviteri.org/2010/06/first-post/",
    "type": "n"
}