{
    "na'vi": "tìkanu",
    "translations": [
        {
            "de": "Intelligenz, Klugheit",
            "en": "intelligence",
            "et": "tarkus",
            "hu": "ész",
            "nl": "inteligentie",
            "pl": "inteligencja",
            "ru": "ум, разум",
            "sv": "intelligens"
        }
    ],
    "pronunciation": [
        "tì-ka-nu",
        2
    ],
    "source": "Frommer (28. April 2010) http://forum.learnnavi.org/language-updates/ayliuo-fa-ni-si-ti/",
    "type": "n"
}