{
    "na'vi": "vawt",
    "translations": [
        {
            "de": "fest, massiv, nicht hohl",
            "en": "solid, not hollow",
            "et": "tahke, mitte õõnes",
            "fr": "solide",
            "hu": "tömör, nem üreges",
            "nl": "vast, solide, niet hol",
            "ru": "плотный, без полостей "
        }
    ],
    "pronunciation": [
        "vawt",
        1
    ],
    "source": "http://naviteri.org/2013/09/on-si-salewfya-shapes-and-directions/ (30 September 2013)",
    "type": "adj"
}