{
    "na'vi": "vingkap",
    "translations": [
        {
            "de": "in den Sinn kommen, einfallen",
            "en": "occur to one, pop into one's mind",
            "et": "pähe turgatama, mõtesse tulema",
            "hu": "eszébe jut, ``beugrik\"",
            "nl": "een ingeving krijgen, een licht opgaan",
            "pl": "przyjść do głowy, przyjść na myśl",
            "ru": "обратить внимание",
            "sv": "inse, komma på"
        }
    ],
    "pronunciation": [
        "ving-kap",
        1
    ],
    "infixes": "v.ingk.ap",
    "type": "v:tr"
}