{
    "na'vi": "ye",
    "translations": [
        {
            "de": "zufrieden; gesättigt, voll",
            "en": "satisfied, content, satiated, full",
            "et": "rahul, rahuldatud, täidetud",
            "fr": "satisfait | content",
            "hu": "(meg)elégedett, hiánytalan, tele",
            "nl": "tevreden, content, vervuld, verzadigd",
            "pl": "zaspokojony, zadowolony, usatysfakcjonowany",
            "ru": "подходящий",
            "sv": "nöjd, belåten"
        }
    ],
    "pronunciation": [
        "ye",
        1
    ],
    "source": "Frommer (05.04.2011) http://naviteri.org/2011/04/%E2%80%99a%E2%80%99awa-li%E2%80%99fyavi-amip%E2%80%94a-few-new-expressions/",
    "type": "adj"
}