{
    "na'vi": "yrr",
    "translations": [
        {
            "de": "wild, natürlich, naturbelassen (etwas in unverändertem, natürlichem Zustand)",
            "en": "wild, natural (something in its original, unmodified, untamperedwith natural state)",
            "et": "loomuomane, looduslik (puutumata ja muutmata tavaolekus olev asi)",
            "hu": "vad, természetes (hamisítatlan, eredeti, változatlan állapotú)",
            "nl": "wild, natuurlijk (iets in natuurlijke, onaangetaste staat)",
            "pl": "dziki, naturalny (będący w naturalnym, niezmienionym stanie)",
            "ru": "нетронутый, натуральный"
        }
    ],
    "pronunciation": [
        "yrr",
        1
    ],
    "type": "adj"
}