{
    "na'vi": "yän",
    "translations": [
        {
            "de": "festmachen, anbringen, festbinden, schnüren",
            "en": "fasten, tie down",
            "et": "kinni siduma",
            "fr": "attacher",
            "hu": "odaerősít, leköt(öz)",
            "nl": "vastmaken, vastbinden",
            "pl": "zamykać, zapinać, przywiązywać",
            "ru": "привязывать, связывать, спутывать, пристегивать",
            "sv": "sätta fast, binda"
        }
    ],
    "pronunciation": [
        "yän",
        1
    ],
    "infixes": "y..än",
    "source": "Taronyu's Dictionary 9.53 < Frommer",
    "type": "v:tr"
}