{
    "na'vi": "zìskrrsom",
    "translations": [
        {
            "de": "Sommer",
            "en": "summer",
            "et": "suvi",
            "fr": "été",
            "hu": "nyár",
            "nl": "zomer"
        }
    ],
    "pronunciation": [
        "zì-skrr-som",
        3
    ],
    "type": "n",
    "source": [
        "Na'viteri (2018-10-30)",
        "http://naviteri.org/2018/10/aysrr-ayvospxi-ayzisikrr-days-months-seasons/"
    ],
    "etymology": [
        "zìsìkrr:n",
        "som:adj"
    ]
}
